{
  "name": "coalossal-gmax",
  "id": 10215,
  "abilities": [
    243,
    49,
    18
  ],
  "types": [
    "rock",
    "fire"
  ],
  "height": 420,
  "weight": 10000,
  "stats": {
    "hp": 110,
    "attack": 80,
    "defense": 120,
    "special-attack": 80,
    "special-defense": 90,
    "speed": 30
  },
  "gender_ratio": 127,
  "held_items": [],
  "egg_groups": [
    10
  ],
  "tm_learnset": [
    241,
    63,
    182,
    76,
    89,
    91,
    115,
    53,
    201,
    126,
    317,
    263,
    156,
    213,
    315,
    503,
    203,
    261,
    416,
    397,
    444,
    360,
    446,
    157,
    214,
    164,
    523
  ],
  "tm_bitfields": [
    169952256,
    306322037,
    33720920,
    32
  ]
}