{
  "name": "skrelp",
  "id": 690,
  "abilities": [
    "poison-point",
    "poison-touch",
    "adaptability"
  ],
  "types": [
    "poison",
    "water"
  ],
  "height": 5,
  "weight": 73,
  "stats": {
    "hp": 50,
    "attack": 60,
    "defense": 60,
    "special-attack": 60,
    "special-defense": 60,
    "speed": 30
  },
  "gender_ratio": 127,
  "held_items": [],
  "egg_groups": [
    2,
    14
  ],
  "tm_learnset": [
    352,
    92,
    258,
    237,
    182,
    240,
    231,
    85,
    247,
    104,
    351,
    188,
    263,
    156,
    213,
    168,
    503,
    203,
    406,
    214,
    207,
    164,
    57,
    127,
    57,
    85,
    127,
    164,
    188,
    200,
    203,
    214,
    231,
    247,
    330,
    390,
    406,
    441,
    482,
    503,
    583,
    599,
    710
  ],
  "tm_bitfields": [
    1099301064,
    134373397,
    2147483648,
    536870920
  ]
}