{
  "name": "pumpkaboo-average",
  "id": 710,
  "abilities": [
    53,
    119,
    15
  ],
  "types": [
    "ghost",
    "grass"
  ],
  "height": 4,
  "weight": 50,
  "stats": {
    "hp": 49,
    "attack": 66,
    "defense": 70,
    "special-attack": 44,
    "special-defense": 55,
    "speed": 51
  },
  "gender_ratio": 127,
  "held_items": [],
  "egg_groups": [
    11
  ],
  "tm_learnset": [
    92,
    331,
    237,
    241,
    113,
    182,
    202,
    219,
    138,
    76,
    94,
    247,
    104,
    53,
    188,
    126,
    263,
    156,
    213,
    168,
    285,
    412,
    203,
    261,
    153,
    148,
    360,
    399,
    157,
    214,
    447,
    207,
    164,
    433,
    249,
    451
  ],
  "tm_bitfields": [
    1616579136,
    572612697,
    274826305,
    4
  ]
}