{
  "name": "bramblin",
  "id": 946,
  "abilities": [
    "wind-rider",
    "infiltrator"
  ],
  "types": [
    "grass",
    "ghost"
  ],
  "height": 6,
  "weight": 6,
  "stats": {
    "hp": 40,
    "attack": 65,
    "defense": 30,
    "special-attack": 45,
    "special-defense": 35,
    "speed": 60
  },
  "gender_ratio": 127,
  "held_items": [],
  "egg_groups": [
    7
  ],
  "tm_learnset": [
    331,
    182,
    202,
    76,
    247,
    263,
    156,
    168,
    412,
    203,
    214,
    447,
    164,
    164,
    191,
    203,
    214,
    247,
    402,
    412,
    437,
    438,
    447
  ],
  "tm_bitfields": [
    1078592000,
    2113537,
    4194304,
    268435456
  ]
}