{
  "name": "slither-wing",
  "id": 988,
  "abilities": [
    281,
    281
  ],
  "types": [
    "bug",
    "fighting"
  ],
  "height": 32,
  "weight": 920,
  "stats": {
    "hp": 85,
    "attack": 135,
    "defense": 79,
    "special-attack": 85,
    "special-defense": 105,
    "speed": 81
  },
  "gender_ratio": 255,
  "held_items": [],
  "egg_groups": [
    15
  ],
  "tm_learnset": [
    339,
    241,
    63,
    182,
    240,
    202,
    89,
    490,
    280,
    201,
    332,
    263,
    156,
    528,
    203,
    261,
    405,
    416,
    214,
    542,
    369,
    164,
    67,
    89,
    141,
    164,
    179,
    203,
    214,
    257,
    276,
    339,
    370,
    394,
    405,
    428,
    484,
    528,
    535,
    542,
    667,
    776
  ],
  "tm_bitfields": [
    2349762816,
    1677722913,
    33554448,
    75501568
  ]
}